sca_tools/__init__.py
sca_tools/_version.py
sca_tools/datasets.py
sca_tools/file_utils.py
sca_tools/graphing.py
sca_tools/sca_agg.py
sca_tools/sca_fit.py
sca_tools/usl.py
sca_tools-0.1.2.dist-info/DESCRIPTION.rst
sca_tools-0.1.2.dist-info/METADATA
sca_tools-0.1.2.dist-info/RECORD
sca_tools-0.1.2.dist-info/WHEEL
sca_tools-0.1.2.dist-info/entry_points.txt
sca_tools-0.1.2.dist-info/metadata.json
sca_tools-0.1.2.dist-info/top_level.txt
tests/__init__.py
tests/conftest.py
tests/test_datasets.py
tests/test_file_utils.py
tests/test_sca_agg.py
tests/test_sca_fit.py
tests/test_usl.py
